launchpadlib/__init__.py
launchpadlib/apps.py
launchpadlib/credentials.py
launchpadlib/errors.py
launchpadlib/launchpad.py
launchpadlib/uris.py
launchpadlib/docs/CONTRIBUTING.rst
launchpadlib/docs/Makefile
launchpadlib/docs/NEWS.rst
launchpadlib/docs/command-line.rst
launchpadlib/docs/conf.py
launchpadlib/docs/hosted-files.rst
launchpadlib/docs/index.rst
launchpadlib/docs/introduction.rst
launchpadlib/docs/operations.rst
launchpadlib/docs/people.rst
launchpadlib/docs/toplevel.rst
launchpadlib/docs/files/mugshot.png
launchpadlib/testing/__init__.py
launchpadlib/testing/helpers.py
launchpadlib/testing/launchpad-wadl.xml
launchpadlib/testing/launchpad.py
launchpadlib/testing/resources.py
launchpadlib/testing/testing-wadl.xml
launchpadlib/testing/tests/__init__.py
launchpadlib/testing/tests/test_launchpad.py
launchpadlib/tests/__init__.py
launchpadlib/tests/test_credential_store.py
launchpadlib/tests/test_http.py
launchpadlib/tests/test_launchpad.py
launchpadlib-2.0.0.dist-info/COPYING.txt
launchpadlib-2.0.0.dist-info/METADATA
launchpadlib-2.0.0.dist-info/WHEEL
launchpadlib-2.0.0.dist-info/top_level.txt
launchpadlib-2.0.0.dist-info/RECORD
