Metadata-Version: 2.1
Name: launchpadlib
Version: 2.0.0
Summary: Script Launchpad through its web services interfaces.  Officially supported.
Home-page: https://help.launchpad.net/API/launchpadlib
Download-URL: https://launchpad.net/launchpadlib/+download
Author: The Launchpad developers
Author-email: launchpadlib@lists.launchpad.net
Maintainer: LAZR Developers
Maintainer-email: lazr-developers@lists.launchpad.net
License: LGPL v3
Project-URL: Source, https://code.launchpad.net/launchpadlib
Project-URL: Issue Tracker, https://bugs.launchpad.net/launchpadlib
Project-URL: Documentation, https://launchpadlib.readthedocs.io/en/latest/
Classifier: Development Status :: 5 - Production/Stable
Classifier: Intended Audience :: Developers
Classifier: License :: OSI Approved :: GNU Library or Lesser General Public License (LGPL)
Classifier: Operating System :: OS Independent
Classifier: Programming Language :: Python
Classifier: Programming Language :: Python :: 2
Classifier: Programming Language :: Python :: 2.7
Classifier: Programming Language :: Python :: 3
Classifier: Programming Language :: Python :: 3.5
Classifier: Programming Language :: Python :: 3.6
Classifier: Programming Language :: Python :: 3.7
Classifier: Programming Language :: Python :: 3.8
Classifier: Programming Language :: Python :: 3.9
Classifier: Programming Language :: Python :: 3.10
Classifier: Programming Language :: Python :: 3.11
Requires-Python: >=3.5
License-File: COPYING.txt
Requires-Dist: httplib2
Requires-Dist: lazr.restfulclient >=0.14.2
Requires-Dist: lazr.uri
Requires-Dist: importlib-metadata ; python_version < "3.8"
Provides-Extra: docs
Requires-Dist: Sphinx ; extra == 'docs'
Provides-Extra: keyring
Requires-Dist: keyring ; extra == 'keyring'
Provides-Extra: test
Requires-Dist: coverage ; extra == 'test'
Requires-Dist: pytest ; extra == 'test'
Provides-Extra: testing
Requires-Dist: testresources ; extra == 'testing'
Requires-Dist: wadllib ; extra == 'testing'
